{
  "caucus": "",
  "special": "",
  "general": true,
  "runoff": true,
  "races": [
    {
      "id": "12597",
      "date": "1/5/2021",
      "test": false,
      "seat": "2",
      "state": "GA",
      "eevp": 19,
      "type": "General Election Runoff",
      "office": "S",
      "results": [
        {
          "id": "12597",
          "updated": 1609894391110,
          "precincts": 2656,
          "reporting": 76,
          "reportingPercentage": 2.86,
          "eevp": 19,
          "winners": [],
          "total": 772886,
          "candidates": [
            {
              "first": "Raphael",
              "last": "Warnock",
              "party": "Dem",
              "id": "69478",
              "votes": 431987,
              "percentage": 55.89
            },
            {
              "first": "Kelly",
              "last": "Loeffler",
              "party": "GOP",
              "id": "67977",
              "votes": 340899,
              "incumbent": true,
              "percentage": 44.11
            }
          ]
        }
      ]
    },
    {
      "id": "12599",
      "date": "1/5/2021",
      "test": false,
      "state": "GA",
      "eevp": 19,
      "type": "General Election Runoff",
      "office": "S",
      "results": [
        {
          "id": "12599",
          "updated": 1609894391110,
          "precincts": 2656,
          "reporting": 71,
          "reportingPercentage": 2.67,
          "eevp": 19,
          "winners": [],
          "total": 770956,
          "candidates": [
            {
              "first": "Jon",
              "last": "Ossoff",
              "party": "Dem",
              "id": "65866",
              "votes": 429270,
              "percentage": 55.68
            },
            {
              "first": "David",
              "last": "Perdue",
              "party": "GOP",
              "id": "63347",
              "votes": 341686,
              "incumbent": true,
              "percentage": 44.32
            }
          ]
        }
      ]
    }
  ]
}