{
  "caucus": "",
  "special": "",
  "general": true,
  "runoff": true,
  "races": [
    {
      "id": "12597",
      "date": "1/5/2021",
      "test": false,
      "seat": "2",
      "state": "GA",
      "eevp": 64,
      "type": "General Election Runoff",
      "office": "S",
      "results": [
        {
          "id": "12597",
          "updated": 1609898820063,
          "precincts": 2656,
          "reporting": 937,
          "reportingPercentage": 35.28,
          "eevp": 64,
          "winners": [],
          "total": 2687820,
          "candidates": [
            {
              "first": "Raphael",
              "last": "Warnock",
              "party": "Dem",
              "id": "69478",
              "votes": 1356784,
              "percentage": 50.48
            },
            {
              "first": "Kelly",
              "last": "Loeffler",
              "party": "GOP",
              "id": "67977",
              "votes": 1331036,
              "incumbent": true,
              "percentage": 49.52
            }
          ]
        }
      ]
    },
    {
      "id": "12599",
      "date": "1/5/2021",
      "test": false,
      "state": "GA",
      "eevp": 64,
      "type": "General Election Runoff",
      "office": "S",
      "results": [
        {
          "id": "12599",
          "updated": 1609898820063,
          "precincts": 2656,
          "reporting": 940,
          "reportingPercentage": 35.39,
          "eevp": 64,
          "winners": [],
          "total": 2687638,
          "candidates": [
            {
              "first": "Jon",
              "last": "Ossoff",
              "party": "Dem",
              "id": "65866",
              "votes": 1347059,
              "percentage": 50.12
            },
            {
              "first": "David",
              "last": "Perdue",
              "party": "GOP",
              "id": "63347",
              "votes": 1340579,
              "incumbent": true,
              "percentage": 49.88
            }
          ]
        }
      ]
    }
  ]
}