{
  "caucus": "",
  "special": "",
  "general": true,
  "runoff": true,
  "races": [
    {
      "id": "12597",
      "date": "1/5/2021",
      "test": false,
      "seat": "2",
      "state": "GA",
      "eevp": 76,
      "type": "General Election Runoff",
      "office": "S",
      "results": [
        {
          "id": "12597",
          "updated": 1609900396940,
          "precincts": 2656,
          "reporting": 1353,
          "reportingPercentage": 50.94,
          "eevp": 76,
          "winners": [],
          "total": 3202126,
          "candidates": [
            {
              "first": "Raphael",
              "last": "Warnock",
              "party": "Dem",
              "id": "69478",
              "votes": 1607932,
              "percentage": 50.21
            },
            {
              "first": "Kelly",
              "last": "Loeffler",
              "party": "GOP",
              "id": "67977",
              "votes": 1594194,
              "incumbent": true,
              "percentage": 49.79
            }
          ]
        }
      ]
    },
    {
      "id": "12599",
      "date": "1/5/2021",
      "test": false,
      "state": "GA",
      "eevp": 76,
      "type": "General Election Runoff",
      "office": "S",
      "results": [
        {
          "id": "12599",
          "updated": 1609900396940,
          "precincts": 2656,
          "reporting": 1358,
          "reportingPercentage": 51.13,
          "eevp": 76,
          "winners": [],
          "total": 3201934,
          "candidates": [
            {
              "first": "David",
              "last": "Perdue",
              "party": "GOP",
              "id": "63347",
              "votes": 1606125,
              "incumbent": true,
              "percentage": 50.16
            },
            {
              "first": "Jon",
              "last": "Ossoff",
              "party": "Dem",
              "id": "65866",
              "votes": 1595809,
              "percentage": 49.84
            }
          ]
        }
      ]
    }
  ]
}