{"timestamp":"2021-01-06T00:26:59.190Z","test":false,"results":{"GA":[{"raceID":"GA-S-12597","summary":{"ruid":"GA","level":"state","precinctsTotal":2656,"precinctsReporting":21,"precinctsReportingPct":0.79,"results":[{"candidateID":"GA22251","voteCount":178837,"votePct":63.99},{"candidateID":"GA22243","voteCount":100645,"votePct":36.01}],"eevp":6.0}},{"raceID":"GA-S-12599","summary":{"ruid":"GA","level":"state","precinctsTotal":2656,"precinctsReporting":23,"precinctsReportingPct":0.87,"results":[{"candidateID":"GA21798","voteCount":169522,"votePct":62.81},{"candidateID":"GA19900","voteCount":100389,"votePct":37.19}],"eevp":6.0}}]}}