[{"stateName":"Georgia","raceTitle":"Senate Runoff","isSwitch":false,"jurisdictionCode":0,"percentReporting":98,"voteTimestamp":"2021-01-06T13:20:13.000Z","candidates":[{"candidateId":19173,"fullName":"Jon Ossoff","firstName":"Jon","lastName":"Ossoff","percent":"50.2","partyCode":"D","winner":false,"isIncumbent":false,"runoffCandidate":false},{"candidateId":63347,"fullName":"David Perdue","firstName":"David","lastName":"Perdue","percent":"49.8","partyCode":"R","winner":false,"isIncumbent":true,"runoffCandidate":false}],"raceKey":"2020-SW-GA","raceTypeCode":"SW"},{"stateName":"Georgia","raceTitle":"Senate Special Runoff","isSwitch":true,"jurisdictionCode":0,"percentReporting":98,"voteTimestamp":"2021-01-06T13:20:27.000Z","candidates":[{"candidateId":20073403,"fullName":"Raphael Warnock","firstName":"Raphael","lastName":"Warnock","percent":"50.6","partyCode":"D","winner":true,"isIncumbent":false,"runoffCandidate":false},{"candidateId":20073404,"fullName":"Kelly Loeffler","firstName":"Kelly","lastName":"Loeffler","percent":"49.4","partyCode":"R","winner":false,"isIncumbent":true,"runoffCandidate":false}],"raceKey":"2020-S2W-GA","raceTypeCode":"S2W"}]